dtcc/__init__.py
dtcc/logging.py
dtcc-0.9.5.dist-info/licenses/LICENSE
dtcc-0.9.5.dist-info/METADATA
dtcc-0.9.5.dist-info/WHEEL
dtcc-0.9.5.dist-info/top_level.txt
dtcc-0.9.5.dist-info/RECORD
