Metadata-Version: 2.4
Name: dtcc
Version: 0.9.5
Summary: DTCC
Author-email: Dag Wästberg <dwastberg@gmail.com>, Anders Logg <logg@chalmers.se>, Vasilis Naserentin <vasilis.naserentin@chalmers.se>, George Spaias <gspaiasa@ece.auth.gr>, Jens Olsson <jens.olsson@chalmersindustriteknik.se>, Themistoklis Arvanitis <thearva@chalmers.se>
Classifier: Intended Audience :: Science/Research
Classifier: Programming Language :: Python :: 3
Classifier: License :: OSI Approved :: MIT License
Requires-Python: >=3.10
License-File: LICENSE
Requires-Dist: dtcc-core>=0.9.5
Requires-Dist: tqdm>=4.67.1
Provides-Extra: test
Requires-Dist: pytest; extra == "test"
Provides-Extra: docs
Requires-Dist: sphinx; extra == "docs"
Requires-Dist: sphinx-immaterial; extra == "docs"
Provides-Extra: viewer
Requires-Dist: dtcc-viewer; extra == "viewer"
Dynamic: license-file
